rotastellar/__init__.py
rotastellar/auth.py
rotastellar/client.py
rotastellar/config.py
rotastellar/errors.py
rotastellar/http.py
rotastellar/types.py
rotastellar-0.1.1.dist-info/METADATA
rotastellar-0.1.1.dist-info/WHEEL
rotastellar-0.1.1.dist-info/licenses/LICENSE
rotastellar-0.1.1.dist-info/RECORD
