Metadata-Version: 2.4
Name: rotastellar
Version: 0.1.1
Summary: Python SDK for RotaStellar - Space Computing Infrastructure
Project-URL: Homepage, https://rotastellar.com
Project-URL: Documentation, https://rotastellar.com/docs
Project-URL: Repository, https://github.com/rotastellar/rotastellar-python
Project-URL: Issues, https://github.com/rotastellar/rotastellar-python/issues
Project-URL: Changelog, https://github.com/rotastellar/rotastellar-python/blob/main/CHANGELOG.md
Author-email: Subhadip Mitra <subhadipmitra@rotastellar.com>, RotaStellar Research <research@rotastellar.com>
Maintainer-email: Subhadip Mitra <subhadipmitra@rotastellar.com>, RotaStellar Research <research@rotastellar.com>
License: MIT
License-File: LICENSE
Keywords: conjunction-analysis,data-center,orbital,orbital-intelligence,satellite,satellite-tracking,space,space-computing
Classifier: Development Status :: 4 - Beta
Classifier: Intended Audience :: Developers
Classifier: Intended Audience :: Science/Research
Classifier: License :: OSI Approved :: MIT License
Classifier: Operating System :: OS Independent
Classifier: Programming Language :: Python :: 3
Classifier: Programming Language :: Python :: 3.9
Classifier: Programming Language :: Python :: 3.10
Classifier: Programming Language :: Python :: 3.11
Classifier: Programming Language :: Python :: 3.12
Classifier: Topic :: Scientific/Engineering :: Astronomy
Classifier: Topic :: Scientific/Engineering :: GIS
Classifier: Typing :: Typed
Requires-Python: >=3.9
Provides-Extra: all
Requires-Dist: httpx>=0.25; extra == 'all'
Requires-Dist: pydantic>=2.0; extra == 'all'
Provides-Extra: async
Requires-Dist: httpx>=0.25; extra == 'async'
Provides-Extra: dev
Requires-Dist: mypy>=1.0; extra == 'dev'
Requires-Dist: pytest-asyncio>=0.21; extra == 'dev'
Requires-Dist: pytest>=7.0; extra == 'dev'
Requires-Dist: ruff>=0.1; extra == 'dev'
Provides-Extra: pydantic
Requires-Dist: pydantic>=2.0; extra == 'pydantic'
